ansible_doc_template_extractor/__init__.py
ansible_doc_template_extractor/_version_scm.py
ansible_doc_template_extractor/cli.py
ansible_doc_template_extractor/schemas/playbook.schema.yml
ansible_doc_template_extractor/schemas/playbook_ansible.schema.yml
ansible_doc_template_extractor/schemas/role.schema.yml
ansible_doc_template_extractor/schemas/role_ansible.schema.yml
ansible_doc_template_extractor/templates/playbook.md.j2
ansible_doc_template_extractor/templates/playbook.rst.j2
ansible_doc_template_extractor/templates/role.md.j2
ansible_doc_template_extractor/templates/role.rst.j2
ansible_doc_template_extractor-0.16.0.dist-info/licenses/LICENSE
ansible_doc_template_extractor-0.16.0.dist-info/METADATA
ansible_doc_template_extractor-0.16.0.dist-info/WHEEL
ansible_doc_template_extractor-0.16.0.dist-info/entry_points.txt
ansible_doc_template_extractor-0.16.0.dist-info/top_level.txt
ansible_doc_template_extractor-0.16.0.dist-info/zip-safe
ansible_doc_template_extractor-0.16.0.dist-info/RECORD
