Metadata-Version: 2.4
Name: ansible-doc-template-extractor
Version: 0.16.0
Summary: Ansible Documentation Template Extractor
Author-email: Andreas Maier <andreas.r.maier@gmx.de>
Maintainer-email: Andreas Maier <andreas.r.maier@gmx.de>
License-Expression: Apache-2.0
Project-URL: Homepage, https://github.com/andy-maier/ansible-doc-template-extractor
Project-URL: Bug Tracker, https://github.com/andy-maier/ansible-doc-template-extractor/issues
Project-URL: Source Code, https://github.com/andy-maier/ansible-doc-template-extractor
Keywords: ansible,documentation,template
Platform: any
Classifier: Development Status :: 5 - Production/Stable
Classifier: Intended Audience :: Information Technology
Classifier: Intended Audience :: System Administrators
Classifier: Topic :: System :: Systems Administration
Classifier: Environment :: Console
Classifier: Operating System :: OS Independent
Classifier: Programming Language :: Python :: 3
Classifier: Programming Language :: Python :: 3.9
Classifier: Programming Language :: Python :: 3.10
Classifier: Programming Language :: Python :: 3.11
Classifier: Programming Language :: Python :: 3.12
Classifier: Programming Language :: Python :: 3.13
Classifier: Programming Language :: Python :: 3.14
Requires-Python: >=3.9
License-File: LICENSE
Requires-Dist: PyYAML>=6.0.2
Requires-Dist: jinja2-ansible-filters>=1.3.1
Requires-Dist: Jinja2>=3.0.3
Requires-Dist: antsibull-docs-parser>=1.2.0
Requires-Dist: jsonschema>=4.23.0
Dynamic: license-file
